LICENSE
MANIFEST.in
README.txt
ez_setup.py
setup.py
bin/soma_delete_all_workflows
bin/soma_restart_workflow
bin/soma_stop_workflow
bin/soma_submit_workflow
bin/soma_workflow_gui
python/soma/__init__.py
python/soma/workflow/MPI_workflow_runner.py
python/soma/workflow/__init__.py
python/soma/workflow/clean_server.py
python/soma/workflow/client.py
python/soma/workflow/client_types.py
python/soma/workflow/configuration.py
python/soma/workflow/connection.py
python/soma/workflow/constants.py
python/soma/workflow/database_server.py
python/soma/workflow/engine.py
python/soma/workflow/engine_types.py
python/soma/workflow/errors.py
python/soma/workflow/observer.py
python/soma/workflow/scheduler.py
python/soma/workflow/setup_client2server.py
python/soma/workflow/setup_server.py
python/soma/workflow/start_database_server.py
python/soma/workflow/start_workflow_engine.py
python/soma/workflow/transfer.py
python/soma/workflow/utils.py
python/soma/workflow/version.py
python/soma/workflow/check_requirement/__init__.py
python/soma/workflow/check_requirement/drmaa.py
python/soma/workflow/gui/GroupInfo.ui
python/soma/workflow/gui/JobInfo.ui
python/soma/workflow/gui/PlotWidget.ui
python/soma/workflow/gui/RequirePW.ui
python/soma/workflow/gui/ServerManagement.ui
python/soma/workflow/gui/ServerNewDlg.ui
python/soma/workflow/gui/TransferInfo.ui
python/soma/workflow/gui/__init__.py
python/soma/workflow/gui/connection_dlg.ui
python/soma/workflow/gui/engine_controller_widget.ui
python/soma/workflow/gui/graphWidget.ui
python/soma/workflow/gui/local_scheduler_widget.ui
python/soma/workflow/gui/main_window.ui
python/soma/workflow/gui/resource_wf_select.ui
python/soma/workflow/gui/search_widget.ui
python/soma/workflow/gui/submissionDlg.ui
python/soma/workflow/gui/sw_mini.ui
python/soma/workflow/gui/wf_status_name_date.ui
python/soma/workflow/gui/workflowExampleDlg.ui
python/soma/workflow/gui/workflowGui.py
python/soma/workflow/gui/icon/done.png
python/soma/workflow/gui/icon/failed.png
python/soma_workflow_test.egg-info/PKG-INFO
python/soma_workflow_test.egg-info/SOURCES.txt
python/soma_workflow_test.egg-info/dependency_links.txt
python/soma_workflow_test.egg-info/requires.txt
python/soma_workflow_test.egg-info/top_level.txt
