Metadata-Version: 1.1
Name: soma-workflow-test
Version: 2.3aa
Summary: 
